sharedbuiltinmutables/README.MD
sharedbuiltinmutables/__init__.py
sharedbuiltinmutables/requirements.txt
sharedbuiltinmutables/thirdparty.json
sharedbuiltinmutables-0.11.dist-info/LICENSE.rst
sharedbuiltinmutables-0.11.dist-info/METADATA
sharedbuiltinmutables-0.11.dist-info/WHEEL
sharedbuiltinmutables-0.11.dist-info/top_level.txt
sharedbuiltinmutables-0.11.dist-info/RECORD
