Metadata-Version: 2.1
Name: sharedbuiltinmutables
Version: 0.11
Summary: Shared list / set / dict across processes / environments
Home-page: https://github.com/hansalemaos/sharedbuiltinmutables
Author: Johannes Fischer
Author-email: aulasparticularesdealemaosp@gmail.com
License: MIT
Keywords: shared,list,set,dict
Classifier: Development Status :: 4 - Beta
Classifier: Programming Language :: Python :: 3 :: Only
Classifier: Programming Language :: Python :: 3.10
Classifier: Topic :: Software Development :: Libraries :: Python Modules
Classifier: Topic :: Utilities
License-File: LICENSE.rst
Requires-Dist: dill
